<?xml version="1.0" encoding="UTF-8"?>
<persistence version="1.0"
	xmlns="http://java.sun.com/xml/ns/persistence"
	xmlns:xsi="http://www.w3.org/2001/XMLSchema-instance"
	xsi:schemaLocation="http://java.sun.com/xml/ns/persistence http://java.sun.com/xml/ns/persistence/persistence_1_0.xsd">
	<persistence-unit name="minibaseUnit"
		transaction-type="RESOURCE_LOCAL">

		<!-- <provider>org.hibernate.ejb.HibernatePersistence</provider> -->
		<!-- non nécessaire avec Hibernate <class>hb.Country</class> -->

		<properties>
			<property name="hibernate.hbm2ddl.auto" value="update" />

			<!-- you can choose to use native hibernate properties -->
			<!-- or -->
			<!-- generic JPA properties, where available -->
			<!-- <property name="hibernate.connection.driver_class" value="org.postgresql.Driver" 
				/> -->
			<!-- <property name="hibernate.connection.url" value="jdbc:postgresql:minibase" 
				/> -->
			<!-- <property name="hibernate.connection.username" value="minibase" /> -->
			<!-- <property name="hibernate.connection.password" value="minibase" /> -->

			<!-- generic JPA properties -->
			<property name="hibernate.connection.url" value="jdbc:mysql://localhost:3306/formationdb?useSSL=false&amp;serverTimezone=UTC" />
			<property name="javax.persistence.jdbc.user" value="root"/>
			<property name="javax.persistence.jdbc.password"
				value="admin" />
			<property name="javax.persistence.jdbc.driver"
				value="com.mysql.jdbc.Driver" />
			<property name="hibernate.dialect" value="org.hibernate.dialect.MySQL5InnoDBDialect" />
		</properties>
	</persistence-unit>
</persistence>	

	